Metadata-Version: 1.1
Name: navschool-oop
Version: 0.0.1
Summary: OOP School Learning by Nav Engineer
Home-page: https://github.com/navapalo/pypi
Author: Nav Engineer
Author-email: navapalo@gmail.com
License: MIT
Download-URL: https://github.com/navapalo/pypi
Keywords: OOP,School,Nav Engineer
Platform: UNKNOWN
Classifier: Development Status :: 3 - Alpha
Classifier: Intended Audience :: Education
Classifier: Topic :: Utilities
Classifier: License :: OSI Approved :: MIT License
Classifier: Programming Language :: Python :: 3
Classifier: Programming Language :: Python :: 3.4
Classifier: Programming Language :: Python :: 3.5
Classifier: Programming Language :: Python :: 3.6
Classifier: Programming Language :: Python :: 3.7
Classifier: Programming Language :: Python :: 3.8
Classifier: Programming Language :: Python :: 3.9
